AUTHORS
CHANGES
LICENSE
MANIFEST.in
README.rst
setup.cfg
setup.py
bk_flower.egg-info/PKG-INFO
bk_flower.egg-info/SOURCES.txt
bk_flower.egg-info/dependency_links.txt
bk_flower.egg-info/entry_points.txt
bk_flower.egg-info/pbr.json
bk_flower.egg-info/requires.txt
bk_flower.egg-info/top_level.txt
docs/Makefile
docs/api.ipynb
docs/api.rst
docs/auth.rst
docs/conf.py
docs/config.rst
docs/docker.rst
docs/features.rst
docs/index.rst
docs/install.rst
docs/man.rst
docs/reverse-proxy.rst
docs/screenshots.rst
docs/tasks.py
docs/tasks_filter.rst
docs/_static/.keep
docs/_templates/localtoc.html
docs/_templates/page.html
docs/_templates/sidebarintro.html
docs/_templates/sidebarlogo.html
docs/_theme/celery/theme.conf
docs/_theme/celery/static/celery.css_t
docs/screenshots/broker.png
docs/screenshots/config.png
docs/screenshots/dashboard.png
docs/screenshots/limits.png
docs/screenshots/monitor.png
docs/screenshots/pool.png
docs/screenshots/queues.png
docs/screenshots/task.png
docs/screenshots/tasks.png
docs/screenshots/worker-tasks.png
flower/__init__.py
flower/__main__.py
flower/app.py
flower/command.py
flower/events.py
flower/options.py
flower/urls.py
flower/api/__init__.py
flower/api/control.py
flower/api/events.py
flower/api/tasks.py
flower/api/workers.py
flower/static/favicon.ico
flower/static/css/bootstrap-datetimepicker.min.css
flower/static/css/bootstrap-responsive.css
flower/static/css/bootstrap-responsive.min.css
flower/static/css/bootstrap.css
flower/static/css/bootstrap.min.css
flower/static/css/flower.css
flower/static/css/images
flower/static/css/jquery-ui.css
flower/static/css/rickshaw.min.css
flower/static/css/images/ui-bg_flat_0_aaaaaa_40x100.png
flower/static/css/images/ui-bg_flat_75_ffffff_40x100.png
flower/static/css/images/ui-bg_glass_55_fbf9ee_1x400.png
flower/static/css/images/ui-bg_glass_65_ffffff_1x400.png
flower/static/css/images/ui-bg_glass_75_dadada_1x400.png
flower/static/css/images/ui-bg_glass_75_e6e6e6_1x400.png
flower/static/css/images/ui-bg_glass_95_fef1ec_1x400.png
flower/static/css/images/ui-bg_highlight-soft_75_cccccc_1x100.png
flower/static/css/images/ui-icons_222222_256x240.png
flower/static/css/images/ui-icons_2e83ff_256x240.png
